main/.SRCINFO
main/VERSION
main/__init__.py
main/alass_encodings.py
main/call_autosubsync.py
main/call_ffsubsync.py
main/constants.py
main/gui.py
main/gui_auto_pairing.py
main/gui_automatic_tab.py
main/gui_batch_mode.py
main/gui_load_library.py
main/gui_log_window.py
main/gui_manual_tab.py
main/gui_multiple_subs.py
main/main.py
main/main_docker.py
main/processed_items_manager.py
main/qt_compat.py
main/subtitle_converter.py
main/subtitle_extractor.py
main/sync_auto.py
main/sync_manual.py
main/texts.py
main/utils.py
main/version.py
main/assets/github.svg
main/assets/icon.icns
main/assets/icon.ico
main/assets/icon.png
main/assets/settings.svg
main/assets/fonts/hack.ttf
main/resources/__init__.py
main/resources/alass-bin/alass-linux64
main/resources/autosubsync/trained-model.bin
assy-6.3.dist-info/METADATA
assy-6.3.dist-info/WHEEL
assy-6.3.dist-info/entry_points.txt
assy-6.3.dist-info/licenses/LICENSE
assy-6.3.dist-info/RECORD
