Metadata-Version: 2.4
Name: assy
Version: 6.3
Summary: Automatic subtitle synchronization tool.
Project-URL: Homepage, https://github.com/denizsafak/AutoSubSync
Project-URL: Documentation, https://github.com/denizsafak/AutoSubSync
Project-URL: Repository, https://github.com/denizsafak/AutoSubSync
Project-URL: Issues, https://github.com/denizsafak/AutoSubSync/issues
Author-email: Deniz Şafak <denizsafak98@gmail.com>
License-Expression: GPL-3.0-or-later
License-File: LICENSE
Keywords: alass,alignment,autosubsync,ffsubsync,media,subtitle,subtitle-sync,synchronization,timing,video
Classifier: Development Status :: 5 - Production/Stable
Classifier: Environment :: X11 Applications :: Qt
Classifier: Intended Audience :: End Users/Desktop
Classifier: License :: OSI Approved :: GNU General Public License v3 or later (GPLv3+)
Classifier: Operating System :: OS Independent
Classifier: Programming Language :: Python :: 3.10
Classifier: Programming Language :: Python :: 3.11
Classifier: Programming Language :: Python :: 3.12
Classifier: Programming Language :: Python :: 3.13
Classifier: Topic :: Multimedia :: Video
Classifier: Topic :: Text Processing
Requires-Python: <3.14,>=3.10
Requires-Dist: autosubsync
Requires-Dist: chardet
Requires-Dist: charset-normalizer
Requires-Dist: faust-cchardet; python_version < '3.13'
Requires-Dist: ffsubsync
Requires-Dist: platformdirs
Requires-Dist: psutil
Requires-Dist: pyqt6
Requires-Dist: requests
Requires-Dist: rich
Requires-Dist: static-ffmpeg
Provides-Extra: dev
Requires-Dist: build; extra == 'dev'
Requires-Dist: pyinstaller; extra == 'dev'
Provides-Extra: torch
Requires-Dist: torch; (python_version <= '3.14') and extra == 'torch'
Requires-Dist: torchaudio; (python_version <= '3.14') and extra == 'torch'
